ayx_plugin_sdk/__init__.py
ayx_plugin_sdk/__main__.py
ayx_plugin_sdk/version.py
ayx_plugin_sdk/assets/TracerBullet/Config.xml
ayx_plugin_sdk/assets/TracerBullet/icon.png
ayx_plugin_sdk/assets/TracerBullet/TracerBulletPlugin/TracerBulletPluginConfig.xml
ayx_plugin_sdk/assets/TracerBullet/TracerBulletPlugin/icon.png
ayx_plugin_sdk/assets/TracerBullet/TracerBulletPlugin/index.html
ayx_plugin_sdk/assets/base_tool_config/Config.xml
ayx_plugin_sdk/assets/base_tool_config/icon.png
ayx_plugin_sdk/assets/executables/yxi-installer.pyz
ayx_plugin_sdk/cli/__init__.py
ayx_plugin_sdk/cli/utilities.py
ayx_plugin_sdk/cli/workspace.py
ayx_plugin_sdk/cli/yxi_builder.py
ayx_plugin_sdk/cli/yxi_installer.py
ayx_plugin_sdk/core/__init__.py
ayx_plugin_sdk/core/constants.py
ayx_plugin_sdk/core/doc_utilities.py
ayx_plugin_sdk/core/environment_base.py
ayx_plugin_sdk/core/exceptions.py
ayx_plugin_sdk/core/field.py
ayx_plugin_sdk/core/input_anchor_base.py
ayx_plugin_sdk/core/input_connection_base.py
ayx_plugin_sdk/core/io_base.py
ayx_plugin_sdk/core/metadata.py
ayx_plugin_sdk/core/observable_mixin.py
ayx_plugin_sdk/core/output_anchor_base.py
ayx_plugin_sdk/core/plugin.py
ayx_plugin_sdk/core/provider_base.py
ayx_plugin_sdk/core/record_packet.py
ayx_plugin_sdk/core/record_packet_base.py
ayx_plugin_sdk/core/register_plugin.py
ayx_plugin_sdk/docs/ayx_plugin_sdk.cli.html
ayx_plugin_sdk/docs/ayx_plugin_sdk.core.html
ayx_plugin_sdk/docs/ayx_plugin_sdk.html
ayx_plugin_sdk/docs/ayx_plugin_sdk.providers.amp_provider.builders.html
ayx_plugin_sdk/docs/ayx_plugin_sdk.providers.amp_provider.html
ayx_plugin_sdk/docs/ayx_plugin_sdk.providers.amp_provider.repositories.html
ayx_plugin_sdk/docs/ayx_plugin_sdk.providers.amp_provider.resources.generated.html
ayx_plugin_sdk/docs/ayx_plugin_sdk.providers.amp_provider.resources.html
ayx_plugin_sdk/docs/ayx_plugin_sdk.providers.e1_provider.html
ayx_plugin_sdk/docs/ayx_plugin_sdk.providers.e1_provider.mock_e1_sdk.AlteryxPythonSDK.html
ayx_plugin_sdk-0.1b4.dist-info/LICENSE
ayx_plugin_sdk-0.1b4.dist-info/METADATA
ayx_plugin_sdk-0.1b4.dist-info/WHEEL
ayx_plugin_sdk-0.1b4.dist-info/entry_points.txt
ayx_plugin_sdk-0.1b4.dist-info/top_level.txt
ayx_plugin_sdk-0.1b4.dist-info/RECORD
