Metadata-Version: 2.1
Name: ayx-plugin-sdk
Version: 0.1b4
Summary: The Python plugin SDK for Alteryx Designer.
Home-page: UNKNOWN
Author: Alteryx, Inc.
Author-email: support@alteryx.com
License: UNKNOWN
Platform: Windows
Classifier: Development Status :: 3 - Alpha
Classifier: Intended Audience :: Developers
Classifier: License :: OSI Approved :: Apache Software License
Classifier: Operating System :: Microsoft :: Windows
Classifier: Programming Language :: Python :: 3.6
Classifier: Topic :: Scientific/Engineering :: Information Analysis
Requires-Python: >=3.8
Requires-Dist: Click (==7.1.2)
Requires-Dist: grpcio (==1.28.1)
Requires-Dist: numpy (==1.19.1)
Requires-Dist: pandas (==1.1.0)
Requires-Dist: psutil (==5.6.3)
Requires-Dist: pydantic (==1.5.1)
Requires-Dist: python-dateutil (==2.8.1)
Requires-Dist: pytz (==2020.1)
Requires-Dist: six (==1.14.0)
Requires-Dist: typer (==0.3.1)
Requires-Dist: xmltodict (==0.12.0)
